{
  "entry": "server.js",
  "files": {
    "23.js": "23.js",
    "components/section-beiträge.js": "components/section-beiträge.js",
    "components/section-call-to-action.js": "components/section-call-to-action.js",
    "components/section-content-beitrag.js": "components/section-content-beitrag.js",
    "components/section-content-navigation-beitrag.js": "components/section-content-navigation-beitrag.js",
    "components/section-content-navigation-video.js": "components/section-content-navigation-video.js",
    "components/section-content-video.js": "components/section-content-video.js",
    "components/section-content.js": "components/section-content.js",
    "components/section-hero-trailer.js": "components/section-hero-trailer.js",
    "components/section-hero.js": "components/section-hero.js",
    "components/section-kontakt.js": "components/section-kontakt.js",
    "components/section-team-member.js": "components/section-team-member.js",
    "components/section-team.js": "components/section-team.js",
    "components/section-videos.js": "components/section-videos.js",
    "components/sectionüber-uns.js": "components/sectionüber-uns.js",
    "pages/aktuelles/_id.js": "pages/aktuelles/_id.js",
    "pages/aktuelles/index.js": "pages/aktuelles/index.js",
    "pages/datenschutzerklärung/index.js": "pages/datenschutzerklärung/index.js",
    "pages/impressum/index.js": "pages/impressum/index.js",
    "pages/index.js": "pages/index.js",
    "pages/login/index.js": "pages/login/index.js",
    "pages/videos/_id.js": "pages/videos/_id.js",
    "pages/videos/index.js": "pages/videos/index.js",
    "server.js": "server.js"
  },
  "maps": {
    "23.js": "23.js.map",
    "components/section-beiträge.js": "components/section-beiträge.js.map",
    "components/section-call-to-action.js": "components/section-call-to-action.js.map",
    "components/section-content-beitrag.js": "components/section-content-beitrag.js.map",
    "components/section-content-navigation-beitrag.js": "components/section-content-navigation-beitrag.js.map",
    "components/section-content-navigation-video.js": "components/section-content-navigation-video.js.map",
    "components/section-content-video.js": "components/section-content-video.js.map",
    "components/section-content.js": "components/section-content.js.map",
    "components/section-hero-trailer.js": "components/section-hero-trailer.js.map",
    "components/section-hero.js": "components/section-hero.js.map",
    "components/section-kontakt.js": "components/section-kontakt.js.map",
    "components/section-team-member.js": "components/section-team-member.js.map",
    "components/section-team.js": "components/section-team.js.map",
    "components/section-videos.js": "components/section-videos.js.map",
    "components/sectionüber-uns.js": "components/sectionüber-uns.js.map",
    "pages/aktuelles/_id.js": "pages/aktuelles/_id.js.map",
    "pages/aktuelles/index.js": "pages/aktuelles/index.js.map",
    "pages/datenschutzerklärung/index.js": "pages/datenschutzerklärung/index.js.map",
    "pages/impressum/index.js": "pages/impressum/index.js.map",
    "pages/index.js": "pages/index.js.map",
    "pages/login/index.js": "pages/login/index.js.map",
    "pages/videos/_id.js": "pages/videos/_id.js.map",
    "pages/videos/index.js": "pages/videos/index.js.map",
    "server.js": "server.js.map"
  }
}